Workbook

Sheet Overview
A2: DORA ICT Risk Register — Musterbank GmbH
A3: EXECUTIVE DASHBOARD — ICT RISK SUMMARY | Musterbank GmbH | DORA (EU 2022/2554)
A4: Total Risks | B4: Critical (16–25) | C4: High (11–15) | D4: Medium (6–10) | E4: Low (1–5) | F4: Open | G4: In Progress | H4: Mitigated | I4: Avg Gross Score | J4: Avg Residual Score
A5: =COUNTA('ICT Risk Register'!A3:A17) -> 15 | B5: =COUNTIF('ICT Risk Register'!M3:M17,"Critical") -> 7 | C5: =COUNTIF('ICT Risk Register'!M3:M17,"High") -> 5 | D5: =COUNTIF('ICT Risk Register'!M3:M17,"Medium") -> 2 | E5: =COUNTIF('ICT Risk Register'!M3:M17,"Low") -> 1 | F5: =COUNTIF('ICT Risk Register'!U3:U17,"Open") -> 8 | G5: =COUNTIF('ICT Risk Register'!U3:U17,"In Progress") -> 6 | H5: =COUNTIF('ICT Risk Register'!U3:U17,"Mitigated") -> 1 | I5: =ROUND(AVERAGE('ICT Risk Register'!L3:L17),1) -> 15.1 | J5: =ROUND(AVERAGE('ICT Risk Register'!R3:R17),1) -> 9.4
A6: KRI BREACH MONITORING | GAP ANALYSIS SUMMARY | VENDOR RISK
A7: KRI Breaches | B7: KRI Amber | C7: KRI Within Tolerance | D7: Gaps: Missing | E7: Gaps: Partial | F7: Gaps: Met | G7: Critical Priority Gaps | H7: Vendors: Critical | I7: Exit Plans Missing | J7: Art.30 Partial
A8: =COUNTIF('ICT Risk Register'!Z3:Z17,"⚠ BREACH – Immediate Action") -> 6 | B8: =COUNTIF('ICT Risk Register'!Z3:Z17,"⚠ Amber – Monitor Closely") -> 5 | C8: =COUNTIF('ICT Risk Register'!Z3:Z17,"✔ Within Tolerance") -> 4 | D8: =COUNTIF('DORA Gap Analysis'!G3:G40,"✘ Missing") -> 10 | E8: =COUNTIF('DORA Gap Analysis'!G3:G40,"◑ Partial") -> 21 | F8: =COUNTIF('DORA Gap Analysis'!G3:G40,"✔ Met") -> 2 | G8: =COUNTIF('DORA Gap Analysis'!J3:J40,"Critical") -> 8 | H8: =COUNTIF('Vendor Risk (Art.28)'!C2:C20,"Critical") -> 5 | I8: =COUNTIF('Vendor Risk (Art.28)'!I2:I20,"✘ Missing") -> 3 | J8: =COUNTIF('Vendor Risk (Art.28)'!E2:E20,"◑ Partial") -> 4
A9: DORA PILLAR RISK BREAKDOWN
A10: DORA Pillar | B10: Risk Count | C10: Critical | D10: High | E10: Medium | F10: Low | G10: Open | H10: KRI Breaches | I10: Avg Gross Score | J10: Avg Residual Score
A11: ICT Risk Management | B11: =COUNTIF('ICT Risk Register'!D3:D17,"ICT Risk Management") -> 6 | C11: =COUNTIFS('ICT Risk Register'!D3:D17,"ICT Risk Management",'ICT Risk Register'!M3:M17,"Critical") -> 1 | D11: =COUNTIFS('ICT Risk Register'!D3:D17,"ICT Risk Management",'ICT Risk Register'!M3:M17,"High") -> 4 | E11: =COUNTIFS('ICT Risk Register'!D3:D17,"ICT Risk Management",'ICT Risk Register'!M3:M17,"Medium") -> 1 | F11: =COUNTIFS('ICT Risk Register'!D3:D17,"ICT Risk Management",'ICT Risk Register'!M3:M17,"Low") -> 0 | G11: =COUNTIFS('ICT Risk Register'!D3:D17,"ICT Risk Management",'ICT Risk Register'!U3:U17,"Open") -> 2 | H11: =COUNTIFS('ICT Risk Register'!D3:D17,"ICT Risk Management",'ICT Risk Register'!Z3:Z17,"⚠ BREACH – Immediate Action") -> 1 | I11: =IFERROR(ROUND(AVERAGEIF('ICT Risk Register'!D3:D17,"ICT Risk Management",'ICT Risk Register'!L3:L17),1),"—") -> 13.8 | J11: =IFERROR(ROUND(AVERAGEIF('ICT Risk Register'!D3:D17,"ICT Risk Management",'ICT Risk Register'!R3:R17),1),"—") -> 6
A12: ICT Incident Mgmt & Reporting | B12: =COUNTIF('ICT Risk Register'!D3:D17,"ICT Incident Management & Reporting") -> 3 | C12: =COUNTIFS('ICT Risk Register'!D3:D17,"ICT Incident Management & Reporting",'ICT Risk Register'!M3:M17,"Critical") -> 1 | D12: =COUNTIFS('ICT Risk Register'!D3:D17,"ICT Incident Management & Reporting",'ICT Risk Register'!M3:M17,"High") -> 1 | E12: =COUNTIFS('ICT Risk Register'!D3:D17,"ICT Incident Management & Reporting",'ICT Risk Register'!M3:M17,"Medium") -> 1 | F12: =COUNTIFS('ICT Risk Register'!D3:D17,"ICT Incident Management & Reporting",'ICT Risk Register'!M3:M17,"Low") -> 0 | G12: =COUNTIFS('ICT Risk Register'!D3:D17,"ICT Incident Management & Reporting",'ICT Risk Register'!U3:U17,"Open") -> 2 | H12: =COUNTIFS('ICT Risk Register'!D3:D17,"ICT Incident Management & Reporting",'ICT Risk Register'!Z3:Z17,"⚠ BREACH – Immediate Action") -> 1 | I12: =IFERROR(ROUND(AVERAGEIF('ICT Risk Register'!D3:D17,"ICT Incident Management & Reporting",'ICT Risk Register'!L3:L17),1),"—") -> 12.3 | J12: =IFERROR(ROUND(AVERAGEIF('ICT Risk Register'!D3:D17,"ICT Incident Management & Reporting",'ICT Risk Register'!R3:R17),1),"—") -> 6.7
A13: Digital Operational Resilience Testing | B13: =COUNTIF('ICT Risk Register'!D3:D17,"Digital Operational Resilience Testing") -> 3 | C13: =COUNTIFS('ICT Risk Register'!D3:D17,"Digital Operational Resilience Testing",'ICT Risk Register'!M3:M17,"Critical") -> 3 | D13: =COUNTIFS('ICT Risk Register'!D3:D17,"Digital Operational Resilience Testing",'ICT Risk Register'!M3:M17,"High") -> 0 | E13: =COUNTIFS('ICT Risk Register'!D3:D17,"Digital Operational Resilience Testing",'ICT Risk Register'!M3:M17,"Medium") -> 0 | F13: =COUNTIFS('ICT Risk Register'!D3:D17,"Digital Operational Resilience Testing",'ICT Risk Register'!M3:M17,"Low") -> 0 | G13: =COUNTIFS('ICT Risk Register'!D3:D17,"Digital Operational Resilience Testing",'ICT Risk Register'!U3:U17,"Open") -> 2 | H13: =COUNTIFS('ICT Risk Register'!D3:D17,"Digital Operational Resilience Testing",'ICT Risk Register'!Z3:Z17,"⚠ BREACH – Immediate Action") -> 2 | I13: =IFERROR(ROUND(AVERAGEIF('ICT Risk Register'!D3:D17,"Digital Operational Resilience Testing",'ICT Risk Register'!L3:L17),1),"—") -> 19 | J13: =IFERROR(ROUND(AVERAGEIF('ICT Risk Register'!D3:D17,"Digital Operational Resilience Testing",'ICT Risk Register'!R3:R17),1),"—") -> 16.3
A14: ICT Third-Party Risk Management | B14: =COUNTIF('ICT Risk Register'!D3:D17,"ICT Third-Party Risk Management") -> 2 | C14: =COUNTIFS('ICT Risk Register'!D3:D17,"ICT Third-Party Risk Management",'ICT Risk Register'!M3:M17,"Critical") -> 2 | D14: =COUNTIFS('ICT Risk Register'!D3:D17,"ICT Third-Party Risk Management",'ICT Risk Register'!M3:M17,"High") -> 0 | E14: =COUNTIFS('ICT Risk Register'!D3:D17,"ICT Third-Party Risk Management",'ICT Risk Register'!M3:M17,"Medium") -> 0 | F14: =COUNTIFS('ICT Risk Register'!D3:D17,"ICT Third-Party Risk Management",'ICT Risk Register'!M3:M17,"Low") -> 0 | G14: =COUNTIFS('ICT Risk Register'!D3:D17,"ICT Third-Party Risk Management",'ICT Risk Register'!U3:U17,"Open") -> 1 | H14: =COUNTIFS('ICT Risk Register'!D3:D17,"ICT Third-Party Risk Management",'ICT Risk Register'!Z3:Z17,"⚠ BREACH – Immediate Action") -> 2 | I14: =IFERROR(ROUND(AVERAGEIF('ICT Risk Register'!D3:D17,"ICT Third-Party Risk Management",'ICT Risk Register'!L3:L17),1),"—") -> 22.5 | J14: =IFERROR(ROUND(AVERAGEIF('ICT Risk Register'!D3:D17,"ICT Third-Party Risk Management",'ICT Risk Register'!R3:R17),1),"—") -> 17
A15: Information Sharing | B15: =COUNTIF('ICT Risk Register'!D3:D17,"Information Sharing") -> 1 | C15: =COUNTIFS('ICT Risk Register'!D3:D17,"Information Sharing",'ICT Risk Register'!M3:M17,"Critical") -> 0 | D15: =COUNTIFS('ICT Risk Register'!D3:D17,"Information Sharing",'ICT Risk Register'!M3:M17,"High") -> 0 | E15: =COUNTIFS('ICT Risk Register'!D3:D17,"Information Sharing",'ICT Risk Register'!M3:M17,"Medium") -> 0 | F15: =COUNTIFS('ICT Risk Register'!D3:D17,"Information Sharing",'ICT Risk Register'!M3:M17,"Low") -> 1 | G15: =COUNTIFS('ICT Risk Register'!D3:D17,"Information Sharing",'ICT Risk Register'!U3:U17,"Open") -> 1 | H15: =COUNTIFS('ICT Risk Register'!D3:D17,"Information Sharing",'ICT Risk Register'!Z3:Z17,"⚠ BREACH – Immediate Action") -> 0 | I15: =IFERROR(ROUND(AVERAGEIF('ICT Risk Register'!D3:D17,"Information Sharing",'ICT Risk Register'!L3:L17),1),"—") -> 4 | J15: =IFERROR(ROUND(AVERAGEIF('ICT Risk Register'!D3:D17,"Information Sharing",'ICT Risk Register'!R3:R17),1),"—") -> 2
A17: RISK SCORING REFERENCE | Gross = L×I | CE: 0%=No Controls | 25%=Weak | 50%=Partial | 75%=Effective | 90%=Strong | 95%=Optimised (max — residual always remains) | Residual = Gross×(1−CE%) | RATINGS: 1–5=Low | 6–10=Medium | 11–15=High | 16–25=Critical | ACTIONS: Low=Accept/Monitor | Medium=Mgmt Review | High=Treatment Plan | Critical=Immediate Escalation
A18: HOW TO USE THIS WORKBOOK
A19: Sheet 2 – ICT Risk Register | B19: Full DORA-compliant ICT risk inventory for Musterbank GmbH. 15 risks across 5 DORA pillars. Columns: Gross Risk (L×I before controls) → CE% (0/25/50/75/90/95 scale, capped at 95%) → Residual Risk (Gross×(1−CE%)) → Required Management Action → KRI current value vs Breach Threshold vs Risk Tolerance. Gross and Residual ratings are formula-driven and update dynamically. Consistent with ISO 27001, NIST SP 800-30, DORA.
A20: Sheet 3 – Risk Matrix | B20: 5×5 heat maps: Gross Risk (before controls) vs Residual Risk (after controls). Rating scale: 1–5 Low | 6–10 Medium | 11–15 High | 16–25 Critical. Control Effectiveness scale: 0%=No Controls | 25%=Weak | 50%=Partial | 75%=Effective | 90%=Strong | 95%=Optimised. KRI vs Risk Tolerance summary with CE% capped at 95% — residual risk always remains.
A21: Sheet 4 – DORA Gap Analysis | B21: Maps all DORA pillars and articles against current Musterbank controls. ✔ Met | ◑ Partial | ✘ Missing. Cross-referenced to ISO 27001:2022, BAIT, MaRisk, NIS2. Includes CIF identification, DORA governance obligations, and NIS2 alignment. 34 requirements assessed. Findings consistent with ICT Risk Register risk descriptions and ratings.
A22: Sheet 5 – Vendor Risk (Art.28) | B22: DORA Article 28 ICT third-party risk register. 8 ICT TPPs assessed: criticality, Art.30 clause status, concentration risk, exit plan status, key finding and action. Findings cross-referenced to Risk Register: AWS (R-003), Temenos (R-010), ABACUS (R-011).
A23: Ownership & Review | B23: Each risk has a named Risk Owner accountable for KRI monitoring and treatment actions. Risk Register reviewed quarterly by Risk Committee. DORA Gap Analysis reviewed before each BaFin supervisory cycle. Prepared by: Shingirai Marenga | ISO 27001 Lead Auditor | CISM | CISSP | June 2026

Sheet ICT Risk Register
A1: ICT Risk Register — Musterbank GmbH | DORA (EU 2022/2554) | Gross Risk = L × I | Control Effectiveness: 0% / 25% / 50% / 75% / 90% / 95% | Residual = Gross × (1−CE%) | CE capped at 95% — residual risk always remains | Rating: 1–5 Low | 6–10 Medium | 11–15 High | 16–25 Critical
A2: Risk ID | B2: Risk Title | C2: Risk Description | D2: DORA Pillar | E2: DORA Article | F2: ISO 27001 Clause | G2: ICT Asset / System | H2: Threat | I2: Vulnerability | J2: Gross Likelihood (1–5) | K2: Gross Impact (1–5) | L2: Gross Risk Score (L×I) | M2: Gross Risk Rating | N2: Required Action | O2: Control / Mitigation Description | P2: Control Owner | Q2: Control Effectiveness (0/25/50/75/90/95%) | R2: Residual Risk Score (Gross×(1−CE%)) | S2: Residual Risk Rating | T2: Required Action | U2: Treatment Status | V2: KRI (Key Risk Indicator) | W2: KRI Current Value | X2: KRI Breach Threshold | Y2: Risk Tolerance | Z2: KRI vs Tolerance | AA2: Risk Treatment | AB2: Risk Owner | AC2: Review Date | AD2: Next Review | AE2: DORA Reporting Obligation | AF2: RTO Target | AG2: RPO Target | AH2: BaFin Notification Deadline
A3: R-015 | B3: BCP/DRP Not Tested | C3: ICT Business Continuity Plan and Disaster Recovery Plan have not been tested for 18 months. 7 critical remediation actions from the 2024 test remain outstanding. RTO/RPO have not been validated against the DORA 4-hour threshold. A real incident would expose unknown gaps across all critical ICT systems. | D3: Digital Operational Resilience Testing | E3: Art. 11 | F3: ISO 27001 A.17.1 | G3: All critical ICT systems (T24, ABACUS, M365, AWS) | H3: Operational failure during live crisis / audit finding | I3: BCP/DRP untested 18 months; 7 open 2024 actions; RTO/RPO unvalidated; no live exercise evidence | J3: 5 | K3: 5 | L3: =J3*K3 -> 25 | M3: Critical | N3: Immediate escalation to senior management / Risk Committee | O3: Annual BCP/DRP tabletop exercise scheduled Q3 2026; full DR test for T24 and ABACUS Q4 2026; 2024 open actions under remediation; results to be reported to Risk Committee | P3: CISO / IT Operations | Q3: 0 | R3: =ROUND(L3*(1-Q3),0) -> 25 | S3: Critical | T3: Immediate escalation to senior management / Risk Committee | U3: Open | V3: Months since last BCP/DRP test; DR test RTO/RPO pass rate (%); outstanding remediation actions from last test (count) | W3: Last BCP test: 18 months ago; Last DR test: 18 months ago; Open 2024 actions: 7 outstanding | X3: BCP not tested >12 months → breach; DR test RTO/RPO failure → escalate; open actions >10 → amber | Y3: BCP tested annually; DR test passes all RTO/RPO targets; zero open critical actions >30d post-test | Z3: ⚠ BREACH – Immediate Action | AA3: Reduce | AB3: CISO | AC3: 2026-10-31 | AD3: 2026-12-31 | AE3: Yes – Art.11 BCP/DRP testing mandatory | AF3: 4 hours | AG3: 1 hour | AH3: 4h if live disaster triggers DORA major incident
A4: R-003 | B4: Cloud Concentration Risk (AWS) | C4: 70% of critical ICT services hosted on a single cloud provider (AWS Frankfurt). No multi-cloud failover, no tested exit plan, and contractual lock-in. Violates DORA Art.29 concentration risk guidance. Exit plan does not exist; AWS outage would cause a systemic bank-wide ICT failure. | D4: ICT Third-Party Risk Management | E4: Art. 28–30 | F4: ISO 27001 A.15.1, A.17.1 | G4: AWS Frankfurt (eu-central-1) | H4: Cloud provider outage / regulatory-mandated exit | I4: Single provider dependency at 70%; no exit plan; no multi-cloud failover; contractual lock-in | J4: 5 | K4: 5 | L4: =J4*K4 -> 25 | M4: Critical | N4: Immediate escalation to senior management / Risk Committee | O4: Multi-cloud roadmap initiated (Azure EU pilot Q3 2026); Art.30 contractual clauses partially inserted (60%); exit plan Phase 1 drafted; concentration risk formally reviewed with CTO | P4: CTO / Procurement | Q4: 0.25 | R4: =ROUND(L4*(1-Q4),0) -> 19 | S4: Critical | T4: Immediate escalation to senior management / Risk Committee | U4: In Progress | V4: Cloud provider concentration ratio (%); exit plan status; Art.30 clause coverage (%); months since last exit plan review | W4: Concentration: 70%; Exit plan: Phase 1 draft only; Art.30 coverage: 60%; Last review: 14 months ago | X4: Concentration >60% AND no tested exit plan → breach; Art.30 <95% by Dec 2026 → amber | Y4: Concentration ≤55%; fully documented and tested exit plan; Art.30 ≥95% coverage | Z4: ⚠ BREACH – Immediate Action | AA4: Reduce | AB4: CTO | AC4: 2026-09-30 | AD4: 2026-12-31 | AE4: Yes – Art.28 Register of Information; Art.29 concentration risk | AF4: 4 hours | AG4: 2 hours | AH4: Art.19 if cloud failure triggers major incident
A5: R-004 | B5: TLPT Scope Gap | C5: Threat-Led Penetration Test (TLPT) has never been conducted. Musterbank exceeds the DORA Art.26 thresholds that make TLPT mandatory. No TIBER-DE-aligned red-team programme exists. Advanced persistent threat exposure in core banking and payment systems is unquantified. BaFin has not been notified. | D5: Digital Operational Resilience Testing | E5: Art. 25–27 | F5: ISO 27001 A.8.8 | G5: Core Banking; Payment Gateway; Internet Banking | H5: Advanced Persistent Threat (APT) / nation-state actor | I5: No TLPT ever conducted; no red-team provider contracted; BaFin not notified; no TIBER-DE scope | J5: 4 | K5: 4 | L5: =J5*K5 -> 16 | M5: Critical | N5: Immediate escalation to senior management / Risk Committee | O5: TLPT scope defined per TIBER-DE methodology; threat intelligence input in progress; red-team provider RFP issued; BaFin pre-notification planned for Q3 2026 | P5: CISO | Q5: 0 | R5: =ROUND(L5*(1-Q5),0) -> 16 | S5: Critical | T5: Immediate escalation to senior management / Risk Committee | U5: Open | V5: TLPT completion status vs DORA deadline; critical finding remediation rate (%); days since last red-team exercise | W5: TLPT status: Not started; Red-team exercises: Never; TIBER-DE scope: In progress | X5: TLPT not commenced by Q4 2026 → regulatory breach; critical findings open >30d → escalation | Y5: TLPT completed per DORA schedule; all critical findings closed ≤14d post-test | Z5: ⚠ BREACH – Immediate Action | AA5: Reduce | AB5: CISO | AC5: 2026-12-31 | AD5: 2027-06-30 | AE5: Yes – Art.26 TLPT obligation mandatory | AF5: N/A | AG5: N/A | AH5: BaFin notification required before TLPT commencement
A6: R-001 | B6: Ransomware on Core Banking | C6: Ransomware attack encrypts TEMENOS T24 core banking; processing outage exceeds 4 hours triggering DORA Art.19 major incident notification to BaFin. EDR coverage at 62%, immutable backups deployed but DR runbook untested in 18 months. | D6: ICT Risk Management | E6: Art. 9–10 | F6: ISO 27001 A.8.8, A.12.3, A.16.1 | G6: TEMENOS T24 Core Banking | H6: Ransomware / Cybercriminal | I6: EDR coverage at 62%; network segmentation incomplete; DR runbook untested 18 months | J6: 4 | K6: 5 | L6: =J6*K6 -> 20 | M6: Critical | N6: Immediate escalation to senior management / Risk Committee | O6: Network micro-segmentation; EDR deployment (62% coverage, 100% target); immutable offsite backups (3-2-1 rule); DR runbook to be tested Q4 2026; BaFin incident response plan in place | P6: CISO / IT Operations | Q6: 0.25 | R6: =ROUND(L6*(1-Q6),0) -> 15 | S6: High | T6: Treatment plan mandatory — senior management review | U6: Open | V6: EDR endpoint coverage (%); RTO achieved in last DR test (hours) | W6: EDR: 62%; Last RTO test: 6.5h (target ≤4h); Backup restore: untested | X6: EDR <100% → amber; last RTO >4h → breach; backup not tested >6m → amber | Y6: EDR ≥100%; RTO ≤4h validated quarterly; backup restore tested every 6 months | Z6: ⚠ BREACH – Immediate Action | AA6: Reduce | AB6: CISO | AC6: 2026-09-30 | AD6: 2026-12-31 | AE6: Yes – Art.19 major incident | AF6: 4 hours | AG6: 1 hour | AH6: 4h initial notification to BaFin / BuBa
A7: R-010 | B7: Vendor Exit Plan Gap (Temenos) | C7: No documented or tested exit strategy exists for Temenos T24 core banking, the bank's most critical ICT dependency. A forced exit would take more than 24 months. Data portability has never been tested. No transition budget has been allocated. This is a mandatory requirement under DORA Art.28(7). | D7: ICT Third-Party Risk Management | E7: Art. 28 | F7: ISO 27001 A.15.1 | G7: TEMENOS T24 Core Banking | H7: Vendor insolvency / regulatory-mandated exit | I7: No exit plan; data portability untested; no transition budget; proprietary data formats; >24-month exit timeline | J7: 4 | K7: 5 | L7: =J7*K7 -> 20 | M7: Critical | N7: Immediate escalation to senior management / Risk Committee | O7: Exit plan Phase 1 draft in progress; data portability scope defined; transition cost estimate commissioned; Art.28(7) compliance gap formally acknowledged | P7: CTO / Procurement | Q7: 0.25 | R7: =ROUND(L7*(1-Q7),0) -> 15 | S7: High | T7: Treatment plan mandatory — senior management review | U7: Open | V7: Exit plan completeness (phase); last data portability test (date); transition cost estimate status; exit plan review age (months) | W7: Exit plan: Phase 1 draft only; Portability test: Never conducted; Cost estimate: In progress; Review age: 8 months | X7: Exit plan not board-approved by Dec 2026 → breach; data portability untested >24m → amber; no cost estimate → amber | Y7: Fully documented and board-approved exit plan; data portability tested biennially; annual review | Z7: ⚠ BREACH – Immediate Action | AA7: Reduce | AB7: CTO | AC7: 2026-12-31 | AD7: 2027-06-30 | AE7: Yes – Art.28(7) exit plans mandatory for critical ICT TPPs | AF7: N/A | AG7: N/A | AH7: N/A – regulatory compliance obligation
A8: R-002 | B8: ICT Incident Under-reporting | C8: ICT incidents misclassified resulting in failure to meet the DORA Art.19 4-hour initial notification deadline to BaFin. No DORA-specific classification matrix in place; average notification time currently 5.2 hours against the 4-hour threshold. | D8: ICT Incident Management & Reporting | E8: Art. 17–20 | F8: ISO 27001 A.5.25, A.5.26 | G8: Incident Mgmt Platform (JIRA / Splunk) | H8: Regulatory non-compliance | I8: No DORA classification matrix; manual escalation; average notification time 5.2h vs 4h threshold | J8: 4 | K8: 4 | L8: =J8*K8 -> 16 | M8: Critical | N8: Immediate escalation to senior management / Risk Committee | O8: DORA incident classification matrix under development; SIEM alerting partially automated; quarterly staff training conducted; playbook drafted but not fully tested | P8: Chief Risk Officer | Q8: 0.25 | R8: =ROUND(L8*(1-Q8),0) -> 12 | S8: High | T8: Treatment plan mandatory — senior management review | U8: In Progress | V8: % incidents correctly classified per DORA matrix; average time-to-initial-notification (hours) | W8: Classification accuracy: 78%; Avg notification time: 5.2h (threshold: 4h) | X8: Classification <95% → amber; notification avg >4h → breach escalation to CRO | Y8: Classification ≥95%; notification avg ≤3h; playbook tested quarterly | Z8: ⚠ BREACH – Immediate Action | AA8: Reduce | AB8: Chief Risk Officer | AC8: 2026-07-31 | AD8: 2026-10-31 | AE8: Yes – Art.19 reporting timeline | AF8: N/A | AG8: N/A | AH8: 4h initial; 72h intermediate; 1 month final
A9: R-009 | B9: Mobile Banking API Vulnerability | C9: SQL injection vulnerability in mobile banking API could allow unauthorised access to customer accounts and mass data breach. DAST pipeline coverage at 74% (target ≥90%); 3 critical vulnerabilities open beyond the 14-day SLA; 2 pen test criticals unresolved. | D9: Digital Operational Resilience Testing | E9: Art. 25 | F9: ISO 27001 A.14.2, A.8.8 | G9: Mobile Banking App (iOS/Android API) | H9: External attacker / Automated scanner | I9: DAST coverage at 74%; 3 critical vulnerabilities open >14d; 2 pen test criticals unresolved; no SAST on all code paths | J9: 4 | K9: 4 | L9: =J9*K9 -> 16 | M9: Critical | N9: Immediate escalation to senior management / Risk Committee | O9: DAST (Burp Suite Enterprise) integrated in CI/CD pipeline; SAST (Checkmarx) deployed; quarterly external pen test; WAF rules reviewed; bug bounty programme launched | P9: Head of Digital / IT Security | Q9: 0.5 | R9: =ROUND(L9*(1-Q9),0) -> 8 | S9: Medium | T9: Management review required — active monitoring | U9: In Progress | V9: DAST pipeline coverage (%); critical/high vulnerabilities open >14 days (count); pen test critical findings outstanding | W9: DAST coverage: 74% (target ≥90%); Criticals open >14d: 3; Pen test criticals outstanding: 2 | X9: DAST coverage <80% → amber; any critical open >14d → breach escalation; pen test criticals unresolved at sign-off → breach | Y9: DAST coverage ≥90%; zero criticals open >14d; zero pen test criticals outstanding at sign-off | Z9: ⚠ Amber – Monitor Closely | AA9: Reduce | AB9: Head of Digital | AC9: 2026-09-30 | AD9: 2026-12-31 | AE9: Yes – Art.25 resilience testing | AF9: N/A | AG9: N/A | AH9: 4h if customer data breach triggers Art.19
A10: R-006 | B10: Insider Data Exfiltration | C10: Privileged employee exfiltrates customer PII and financial data via USB or cloud upload prior to resignation. DLP policy covers 72% of violation SLAs. No User Behaviour Analytics deployed. Joiner/Mover/Leaver process gaps identified. DSGVO 72h breach notification obligation applies. | D10: ICT Risk Management | E10: Art. 9–10 | F10: ISO 27001 A.9.2, A.12.4 | G10: DLP (Forcepoint); Active Directory | H10: Malicious or negligent insider | I10: DLP SLA compliance at 72%; no UBA tooling; JML process gaps; privileged access recertification 85% complete | J10: 3 | K10: 4 | L10: =J10*K10 -> 12 | M10: High | N10: Treatment plan mandatory — senior management review | O10: DLP policy updated and tuned; UBA solution in procurement (shortlist complete); HR JML process reviewed; quarterly privileged access recertification initiated | P10: CISO / HR | Q10: 0.5 | R10: =ROUND(L10*(1-Q10),0) -> 6 | S10: Medium | T10: Management review required — active monitoring | U10: Open | V10: DLP policy violations reviewed within SLA (%); privileged access recertification completion (%); UBA go-live status | W10: DLP SLA: 72% (target ≥95%); Recertification: 85% complete; UBA: procurement stage | X10: DLP SLA <90% → amber; recertification <100% → escalate; any confirmed exfiltration event → critical | Y10: DLP SLA ≥95%; recertification 100% on schedule; UBA live by Q3 2026 | Z10: ⚠ Amber – Monitor Closely | AA10: Reduce | AB10: CISO | AC10: 2026-09-30 | AD10: 2026-12-31 | AE10: Yes – Art.9; DSGVO Art.33 72h notification if PII breach confirmed | AF10: N/A | AG10: N/A | AH10: 72h DSGVO notification if PII breach confirmed
A11: R-011 | B11: Regulatory Reporting System Failure (ABACUS) | C11: ABACUS regulatory reporting system failure at month-end prevents submission of BaFin COREP/FINREP reports, resulting in a regulatory breach and potential supervisory fine. DR instance provisioned but April 2026 drill was only a partial pass. Manual fallback last tested March 2026. | D11: ICT Incident Management & Reporting | E11: Art. 19 | F11: ISO 27001 A.17.1 | G11: ABACUS Regulatory Reporting (Wolters Kluwer) | H11: System failure / data quality error | I11: Single ABACUS instance; DR drill partial pass April 2026; manual fallback process not fully validated | J11: 3 | K11: 4 | L11: =J11*K11 -> 12 | M11: High | N11: Treatment plan mandatory — senior management review | O11: DR instance provisioned in secondary data centre; manual fallback procedure documented and tabletop-tested; automated data validation scripts deployed; monthly DR failover drill scheduled | P11: CFO / IT Operations | Q11: 0.5 | R11: =ROUND(L11*(1-Q11),0) -> 6 | S11: Medium | T11: Management review required — active monitoring | U11: Open | V11: ABACUS availability during all regulatory reporting windows (%); DR failover drill result (pass/fail); manual fallback last tested (date) | W11: Availability: 99.1% (target ≥99.8%); DR drill: April 2026 partial pass; Fallback last tested: March 2026 | X11: Availability <99.5% in any reporting window → amber; DR drill failure → escalate to CFO; fallback untested >6m → amber | Y11: Availability ≥99.8% in all reporting windows; DR drill passes monthly; fallback tested quarterly | Z11: ⚠ Amber – Monitor Closely | AA11: Reduce | AB11: CFO | AC11: 2026-10-31 | AD11: 2027-01-31 | AE11: Yes – Art.19 regulatory reporting obligation | AF11: 4 hours | AG11: 1 hour | AH11: Immediate BaFin notification if reporting deadline cannot be met
A12: R-013 | B12: ICT Change Management Failure | C12: Uncontrolled production change to TEMENOS T24 causes a 6-hour processing outage and data inconsistency. CAB reinstated; however rollback plan coverage at 82% and 2 change-related incidents occurred last month. | D12: ICT Risk Management | E12: Art. 9(4) | F12: ISO 27001 A.12.1, A.14.2 | G12: TEMENOS T24 / CAB Process (JIRA) | H12: Operational / human error | I12: CAB only recently reinstated; rollback plan coverage 82%; emergency changes bypass process; 2 incidents last month | J12: 3 | K12: 4 | L12: =J12*K12 -> 12 | M12: High | N12: Treatment plan mandatory — senior management review | O12: CAB reinstated with mandatory approval gates; rollback plan required for all major and emergency changes; PIR mandatory post-change; monthly change-incident trend reporting to IT Management | P12: IT Operations Manager | Q12: 0.5 | R12: =ROUND(L12*(1-Q12),0) -> 6 | S12: Medium | T12: Management review required — active monitoring | U12: In Progress | V12: % major changes with documented rollback plan; change-related production incidents per month; PIR completion rate (%) | W12: Rollback plan coverage: 82% (target 100%); Change incidents: 2 last month (tolerance ≤1); PIR rate: 91% | X12: Rollback plan <100% → amber; >2 change incidents/month → escalate; PIR rate <90% → amber | Y12: 100% rollback plan coverage; ≤1 change incident/month; PIR rate 100% within 5 days of change | Z12: ⚠ Amber – Monitor Closely | AA12: Reduce | AB12: IT Operations Manager | AC12: 2026-08-31 | AD12: 2026-11-30 | AE12: Yes – Art.9(4) ICT change management | AF12: 4 hours | AG12: 1 hour | AH12: 4h if change causes DORA-classifiable major incident
A13: R-005 | B13: SWIFT Messaging Fraud | C13: Compromised SWIFT operator credentials used to initiate fraudulent MT103 payment messages resulting in potential EUR multi-million financial loss. Hardware MFA now enforced on 95% of operators (5% gap remaining); dual-authorisation controls active for payments >EUR 100k. | D13: ICT Risk Management | E13: Art. 9 | F13: ISO 27001 A.9.4, A.12.4 | G13: SWIFT Alliance Gateway | H13: Insider threat / Business Email Compromise | I13: MFA adoption at 95% (5% gap); SWIFT CSCF v2024 compliance not yet fully verified | J13: 3 | K13: 5 | L13: =J13*K13 -> 15 | M13: High | N13: Treatment plan mandatory — senior management review | O13: Hardware MFA (YubiKey) enforced on SWIFT operators; dual-authorisation mandatory >EUR 100k; SWIFT CSCF v2024 compliance verification in progress; anomaly detection active on all SWIFT transactions | P13: Head of Payments / IT Security | Q13: 0.75 | R13: =ROUND(L13*(1-Q13),0) -> 4 | S13: Low | T13: Accept and monitor — annual review sufficient | U13: In Progress | V13: MFA adoption rate across all SWIFT operators (%); SWIFT anomaly alerts triggered per month; dual-auth exception count per month | W13: MFA adoption: 95% (target 100%); Anomaly alerts: 1/month (investigated, no breach); Dual-auth exceptions: 0 | X13: Any unapproved SWIFT transaction → critical; MFA <100% → breach; dual-auth exception → immediate review | Y13: MFA 100% of all operators; zero unapproved transactions; dual-auth exceptions = 0 | Z13: ✔ Within Tolerance | AA13: Reduce | AB13: Head of Payments | AC13: 2026-08-31 | AD13: 2026-11-30 | AE13: Yes – Art.9; Art.19 if material financial loss | AF13: N/A | AG13: N/A | AH13: Immediate escalation; Art.19 within 4h if financial loss is material
A14: R-008 | B14: Active Directory Domain Compromise | C14: Attacker compromises AD domain admin account via pass-the-hash or Kerberoasting, enabling lateral movement across all bank systems. CyberArk PAM deployed at 88% coverage; 2 shared admin accounts remain outstanding. AD tiering model enforced. | D14: ICT Risk Management | E14: Art. 9 | F14: ISO 27001 A.9.2, A.9.4 | G14: Active Directory / Azure AD | H14: Credential theft / Pass-the-hash / Kerberoasting | I14: PAM coverage at 88%; 2 shared admin accounts outstanding; AD tiering partially complete | J14: 3 | K14: 5 | L14: =J14*K14 -> 15 | M14: High | N14: Treatment plan mandatory — senior management review | O14: CyberArk PAM deployed (88% coverage, target 100%); AD 3-tier model enforced; hardware MFA on admin accounts (100%); privileged session recording active; quarterly purple-team exercise | P14: IT Security Manager | Q14: 0.75 | R14: =ROUND(L14*(1-Q14),0) -> 4 | S14: Low | T14: Accept and monitor — annual review sufficient | U14: In Progress | V14: PAM vault coverage (% privileged accounts); shared admin accounts outstanding (count); admin MFA adoption (%); last purple-team result | W14: PAM coverage: 88% (target 100%); Shared admins: 2 remaining; Admin MFA: 100%; Purple team Q1 2026: pass | X14: PAM coverage <95% → amber; any shared admin account detected → breach; admin MFA <100% → breach | Y14: PAM 100%; zero shared admin accounts; MFA 100%; quarterly purple-team: no critical findings | Z14: ✔ Within Tolerance | AA14: Reduce | AB14: IT Security Manager | AC14: 2026-08-31 | AD14: 2026-11-30 | AE14: Yes – Art.9 ICT security controls | AF14: N/A | AG14: N/A | AH14: Immediate; Art.19 if systems-wide impact confirmed
... A17: R-012 | B17: Business Email Compromise (BEC) | C17: CEO/CFO email account spoofed; finance team transfers EUR 500k to fraudulent account. DMARC/DKIM/SPF now enforced on all domains; phishing click rate at 4.2% (within ≤5% tolerance); zero BEC incidents in last 12 months. Controls substantially effective. | D17: ICT Risk Management | E17: Art. 9 | F17: ISO 27001 A.12.2, A.16.1 | G17: Microsoft 365 / Email Gateway | H17: Social engineering / BEC fraud | I17: Historical: DMARC not enforced. Current: all controls active; click rate 4.2%; 0 incidents | J17: 3 | K17: 3 | L17: =J17*K17 -> 9 | M17: Medium | N17: Management review required — active monitoring | O17: DMARC/DKIM/SPF enforced on all domains; mandatory voice callback for payments >EUR 25k; quarterly phishing simulation; Microsoft Defender ATP advanced email filtering active | P17: CISO / Head of Finance | Q17: 0.9 | R17: =ROUND(L17*(1-Q17),0) -> 1 | S17: Low | T17: Accept and monitor — annual review sufficient | U17: Mitigated | V17: Phishing simulation click-through rate (%); DMARC enforcement status; BEC incidents in rolling 12-month period | W17: Click rate: 4.2% (tolerance ≤5%); DMARC: enforced all domains; BEC incidents: 0 last 12 months | X17: Click rate >8% → mandatory retraining; any DMARC gap → immediate remediation; any successful BEC → critical | Y17: Click rate ≤5%; DMARC enforced 100%; zero successful BEC in any 12-month period | Z17: ✔ Within Tolerance | AA17: Accept (residual) | AB17: CISO | AC17: 2026-12-31 | AD17: 2027-03-31 | AE17: Yes – Art.9; Art.19 if financial loss exceeds major incident threshold | AF17: N/A | AG17: N/A | AH17: 4h if financial loss triggers DORA major incident
A19: SCORING | Gross Risk = Likelihood (1–5) × Impact (1–5) | CE Scale: 0%=No Controls 25%=Weak 50%=Partial 75%=Effective 90%=Strong 95%=Optimised (capped at 95% — residual risk always remains per ISO 27001 / NIST SP 800-30) | Residual Risk = Gross × (1−CE%) | RATINGS: 1–5 Low | 6–10 Medium | 11–15 High | 16–25 Critical | ACTIONS: Low=Accept & Monitor | Medium=Management Review | High=Treatment Plan Mandatory | Critical=Immediate Escalation

Sheet Risk Matrix
A1: ICT Risk Heat Map — Musterbank GmbH | DORA (EU 2022/2554) | Rating Scale: 1–5 Low | 6–10 Medium | 11–15 High | 16–25 Critical | Left: Gross Risk (Before Controls) | Right: Residual Risk (After Controls, CE% capped at 95%)
A2: GROSS RISK (Before Controls) | J2: RESIDUAL RISK (After Controls, CE ≤95%)
A3: IMPACT ▲ | B3: 5 | E3: R-005 R-008 | F3: R-001 R-010 | G3: R-003 R-015 | J3: IMPACT ▲ | K3: 5 | P3: R-015
B4: 4 | E4: R-006 R-011 R-013 | F4: R-002 R-004 R-009 | K4: 4 | N4: R-001 R-010 | O4: R-003 R-004
B5: 3 | E5: R-007 R-012 | K5: 3 | M5: R-006 R-011 R-013 | N5: R-002 R-009
B6: 2 | D6: R-014 | K6: 2 | M6: R-005 R-007 R-008
B7: 1 | K7: 1 | L7: R-012 R-014
C9: 1 | D9: 2 | E9: 3 | F9: 4 | G9: 5 | L9: 1 | M9: 2 | N9: 3 | O9: 4 | P9: 5
B10: LIKELIHOOD ▶ | K10: LIKELIHOOD ▶
A13: RISK RATING SCALE | Banking / DORA Approach | Tied to required management actions
A14: CRITICAL Score 16–25 Immediate escalation to senior management and Risk Committee. DORA Art.19 notification to BaFin highly likely. Board-level visibility required. Treatment plan with weekly progress updates. | F14: HIGH Score 11–15 Treatment plan mandatory. Senior management review within 48 hours. Risk owner accountable for remediation milestones. Monthly reporting to Risk Committee. | K14: MEDIUM Score 6–10 Management review required. Risk owner to implement planned controls. Active monitoring via KRI dashboard. Review at next quarterly Risk Committee cycle. | P14: LOW Score 1–5 Accept and monitor. Risk within board-approved tolerance. Monitor via KRI dashboard. Annual review sufficient. No immediate treatment required.
A21: CONTROL EFFECTIVENESS & ADEQUACY SCALE | ISO 27001 / NIST SP 800-30 aligned | CE capped at 95% — residual risk always remains even with the strongest controls
A22: 0% NO CONTROLS No meaningful controls. Risk fully unmitigated. Immediate action required. | D22: 25% WEAK Controls exist but have critical gaps; easily bypassed or untested. | G22: 50% PARTIAL Controls partially effective; gaps identified; active remediation in progress. | J22: 75% EFFECTIVE Controls broadly effective; some residual gaps; monitored via KRI. | N22: 90% STRONG Robust controls in place; regularly tested; minor residual gaps only. | R22: 95% OPTIMISED Comprehensive controls; fully tested; evidence-based assurance. Max CE.
A30: KRI vs RISK TOLERANCE MONITORING SUMMARY
A31: Risk ID | B31: Risk Title | E31: CE (%) | F31: Gross Score | G31: Gross Rating | I31: Residual Score | J31: Residual Rating | L31: KRI (Indicator) | Q31: Current KRI Value | Y31: KRI Breach Threshold | AG31: Risk Tolerance | AO31: KRI Status
A32: R-001 | B32: Ransomware on Core Banking | E32: 25% | F32: 20 | G32: Critical | I32: 15 | J32: High | L32: EDR endpoint coverage (%); RTO achieved in last DR test (hours) | Q32: EDR: 62%; Last RTO test: 6.5h (target ≤4h); Backup restore: untested | Y32: EDR <100% → amber; last RTO >4h → breach; backup not tested >6m → amber | AG32: EDR ≥100%; RTO ≤4h validated quarterly; backup restore tested every 6 months | AO32: ⚠ BREACH
A33: R-002 | B33: ICT Incident Under-reporting | E33: 25% | F33: 16 | G33: Critical | I33: 12 | J33: High | L33: % incidents correctly classified per DORA matrix; average time-to-initial-notification (hours) | Q33: Classification accuracy: 78%; Avg notification time: 5.2h (threshold: 4h) | Y33: Classification <95% → amber; notification avg >4h → breach escalation to CRO | AG33: Classification ≥95%; notification avg ≤3h; playbook tested quarterly | AO33: ⚠ BREACH
A34: R-003 | B34: Cloud Concentration Risk (AWS) | E34: 25% | F34: 25 | G34: Critical | I34: 19 | J34: Critical | L34: Cloud provider concentration ratio (%); exit plan status; Art.30 clause coverage (%); months since last exit plan review | Q34: Concentration: 70%; Exit plan: Phase 1 draft only; Art.30 coverage: 60%; Last review: 14 months ago | Y34: Concentration >60% AND no tested exit plan → breach; Art.30 <95% by Dec 2026 → amber | AG34: Concentration ≤55%; fully documented and tested exit plan; Art.30 ≥95% coverage | AO34: ⚠ BREACH
A35: R-004 | B35: TLPT Scope Gap | E35: 0% | F35: 16 | G35: Critical | I35: 16 | J35: Critical | L35: TLPT completion status vs DORA deadline; critical finding remediation rate (%); days since last red-team exercise | Q35: TLPT status: Not started; Red-team exercises: Never; TIBER-DE scope: In progress | Y35: TLPT not commenced by Q4 2026 → regulatory breach; critical findings open >30d → escalation | AG35: TLPT completed per DORA schedule; all critical findings closed ≤14d post-test | AO35: ⚠ BREACH
A36: R-005 | B36: SWIFT Messaging Fraud | E36: 75% | F36: 15 | G36: High | I36: 4 | J36: Low | L36: MFA adoption rate across all SWIFT operators (%); SWIFT anomaly alerts triggered per month; dual-auth exception count per month | Q36: MFA adoption: 95% (target 100%); Anomaly alerts: 1/month (investigated, no breach); Dual-auth exceptions: 0 | Y36: Any unapproved SWIFT transaction → critical; MFA <100% → breach; dual-auth exception → immediate review | AG36: MFA 100% of all operators; zero unapproved transactions; dual-auth exceptions = 0 | AO36: ✔ Tolerance
A37: R-006 | B37: Insider Data Exfiltration | E37: 50% | F37: 12 | G37: High | I37: 6 | J37: Medium | L37: DLP policy violations reviewed within SLA (%); privileged access recertification completion (%); UBA go-live status | Q37: DLP SLA: 72% (target ≥95%); Recertification: 85% complete; UBA: procurement stage | Y37: DLP SLA <90% → amber; recertification <100% → escalate; any confirmed exfiltration event → critical | AG37: DLP SLA ≥95%; recertification 100% on schedule; UBA live by Q3 2026 | AO37: ⚠ Amber
A38: R-007 | B38: Payment Gateway DDoS | E38: 75% | F38: 9 | G38: Medium | I38: 2 | J38: Low | L38: Payment gateway monthly availability (%); DDoS incidents per period; time-to-mitigation for last DDoS event (minutes) | Q38: Availability: 99.6% (SLA ≥99.9%); DDoS incidents: 1 (mitigated in 22 min); BGP failover: tested | Y38: Availability <99.5% in any calendar month → amber breach; DDoS mitigation >60 min → escalate | AG38: Availability ≥99.9% sustained; mitigation ≤15 min; zero unmitigated incidents | AO38: ✔ Tolerance
A39: R-008 | B39: Active Directory Domain Compromise | E39: 75% | F39: 15 | G39: High | I39: 4 | J39: Low | L39: PAM vault coverage (% privileged accounts); shared admin accounts outstanding (count); admin MFA adoption (%); last purple-team result | Q39: PAM coverage: 88% (target 100%); Shared admins: 2 remaining; Admin MFA: 100%; Purple team Q1 2026: pass | Y39: PAM coverage <95% → amber; any shared admin account detected → breach; admin MFA <100% → breach | AG39: PAM 100%; zero shared admin accounts; MFA 100%; quarterly purple-team: no critical findings | AO39: ✔ Tolerance
A40: R-009 | B40: Mobile Banking API Vulnerability | E40: 50% | F40: 16 | G40: Critical | I40: 8 | J40: Medium | L40: DAST pipeline coverage (%); critical/high vulnerabilities open >14 days (count); pen test critical findings outstanding | Q40: DAST coverage: 74% (target ≥90%); Criticals open >14d: 3; Pen test criticals outstanding: 2 | Y40: DAST coverage <80% → amber; any critical open >14d → breach escalation; pen test criticals unresolved at sign-off → breach | AG40: DAST coverage ≥90%; zero criticals open >14d; zero pen test criticals outstanding at sign-off | AO40: ⚠ Amber
A41: R-010 | B41: Vendor Exit Plan Gap (Temenos) | E41: 25% | F41: 20 | G41: Critical | I41: 15 | J41: High | L41: Exit plan completeness (phase); last data portability test (date); transition cost estimate status; exit plan review age (months) | Q41: Exit plan: Phase 1 draft only; Portability test: Never conducted; Cost estimate: In progress; Review age: 8 months | Y41: Exit plan not board-approved by Dec 2026 → breach; data portability untested >24m → amber; no cost estimate → amber | AG41: Fully documented and board-approved exit plan; data portability tested biennially; annual review | AO41: ⚠ BREACH
A42: R-011 | B42: Regulatory Reporting System Failure (ABACUS) | E42: 50% | F42: 12 | G42: High | I42: 6 | J42: Medium | L42: ABACUS availability during all regulatory reporting windows (%); DR failover drill result (pass/fail); manual fallback last tested (date) | Q42: Availability: 99.1% (target ≥99.8%); DR drill: April 2026 partial pass; Fallback last tested: March 2026 | Y42: Availability <99.5% in any reporting window → amber; DR drill failure → escalate to CFO; fallback untested >6m → amber | AG42: Availability ≥99.8% in all reporting windows; DR drill passes monthly; fallback tested quarterly | AO42: ⚠ Amber
A43: R-012 | B43: Business Email Compromise (BEC) | E43: 90% | F43: 9 | G43: Medium | I43: 1 | J43: Low | L43: Phishing simulation click-through rate (%); DMARC enforcement status; BEC incidents in rolling 12-month period | Q43: Click rate: 4.2% (tolerance ≤5%); DMARC: enforced all domains; BEC incidents: 0 last 12 months | Y43: Click rate >8% → mandatory retraining; any DMARC gap → immediate remediation; any successful BEC → critical | AG43: Click rate ≤5%; DMARC enforced 100%; zero successful BEC in any 12-month period | AO43: ✔ Tolerance
... A46: R-015 | B46: BCP/DRP Not Tested | E46: 0% | F46: 25 | G46: Critical | I46: 25 | J46: Critical | L46: Months since last BCP/DRP test; DR test RTO/RPO pass rate (%); outstanding remediation actions from last test (count) | Q46: Last BCP test: 18 months ago; Last DR test: 18 months ago; Open 2024 actions: 7 outstanding | Y46: BCP not tested >12 months → breach; DR test RTO/RPO failure → escalate; open actions >10 → amber | AG46: BCP tested annually; DR test passes all RTO/RPO targets; zero open critical actions >30d post-test | AO46: ⚠ BREACH

Sheet DORA Gap Analysis
A1: DORA Gap Analysis — Musterbank GmbH | ISO 27001 Lead Auditor Review | DORA (EU 2022/2554) × ISO 27001:2022 × BAIT × MaRisk × NIS2 | ✔ Met | ◑ Partial | ✘ Missing
A2: DORA Pillar | B2: DORA Requirement | C2: DORA Article | D2: ISO 27001:2022 Mapping | E2: BAIT / MaRisk Ref | F2: Current Control at Musterbank | G2: Gap Status | H2: Gap Description | I2: Remediation Action | J2: Priority | K2: Target Date | L2: Owner
A3: ICT Risk Management | B3: ICT risk management framework | C3: Art. 5–6 | D3: Cl. 6.1, 8.2 | E3: MaRisk AT 7.2; BAIT §2 | F3: ICT risk register in Excel; quarterly Risk Committee review | G3: ◑ Partial | H3: Framework not formally documented as DORA-compliant; no board-approved ICT risk appetite statement; Art.6 three-line model not evidenced | I3: Formalise ICT risk management framework per Art.6; draft and obtain board approval for ICT risk appetite; document three-line model assignment | J3: High | K3: 2026-09-30 | L3: CRO / CISO
A4: ICT Risk Management | B4: ICT asset classification and inventory | C4: Art. 8 | D4: A.8.1, A.8.8 | E4: BAIT §4; MaRisk AT 7.2 | F4: CMDB in ServiceNow; patching tracked via Qualys | G4: ◑ Partial | H4: CMDB not fully validated; shadow IT not captured; Register of Information (DORA Art.28 EBA ITS) not linked to CMDB; criticality ratings not DORA-aligned | I4: Complete CMDB audit; classify assets per DORA criticality tiers; link to Register of Information; shadow IT discovery tooling | J4: High | K4: 2026-10-31 | L4: IT Asset Manager
A5: ICT Risk Management | B5: ICT security policies and controls | C5: Art. 9 | D5: A.5, A.6, A.8 | E5: BAIT §3; MaRisk AT 7.2 | F5: ISO 27001 ISMS policy suite in place; annual review cycle | G5: ✔ Met | H5: Policies aligned to ISO 27001; DORA Art.9 requirements covered by existing ISMS; annual DORA Art.9 checklist review needed | I5: Annual ISMS review to include explicit DORA Art.9 checklist; evidence DORA alignment in policy headers | J5: Low | K5: 2026-12-31 | L5: CISO
A6: ICT Risk Management | B6: ICT risk tolerance and appetite | C6: Art. 6(8) | D6: Cl. 6.1 | E6: MaRisk AT 2.2; BAIT §2 | F6: No board-approved ICT risk appetite or tolerance statement | G6: ✘ Missing | H6: DORA Art.6(8) requires management body to set and own ICT risk tolerance; no documented appetite; risk register lacks tolerance thresholds | I6: Draft ICT risk appetite statement; present to Management Board for approval; cascade to risk register KRI thresholds | J6: Critical | K6: 2026-09-30 | L6: CRO
A7: ICT Risk Management | B7: Business continuity and backup | C7: Art. 12 | D7: A.17 | E7: BAIT §7; MaRisk AT 7.3 | F7: BCP exists; daily backups to S3; DR plan documented | G7: ◑ Partial | H7: BCP/DR not tested in 18 months; RTO/RPO not validated against DORA 4h threshold; backup restoration not tested; Art.12 requires documented backup and recovery testing | I7: Schedule annual DR test; validate RTO ≤4h and RPO ≤1h per DORA; test backup restoration quarterly; document and report test results | J7: Critical | K7: 2026-10-31 | L7: CISO / IT Ops
A8: ICT Risk Management | B8: ICT change management | C8: Art. 9(4) | D8: A.8.32 | E8: BAIT §5 | F8: CAB process in JIRA; change records maintained | G8: ◑ Partial | H8: Rollback plans not mandatory; emergency changes bypass CAB; audit trail gaps; Art.9(4) requires all ICT changes to be managed and documented | I8: Mandatory rollback plan for all major and emergency changes; tighten emergency CAB; automated change audit trail; monthly trend reporting | J8: High | K8: 2026-08-31 | L8: IT Ops Manager
A9: ICT Risk Management | B9: ICT capacity and performance | C9: Art. 9(3) | D9: A.8.6 | E9: BAIT §4 | F9: Infrastructure monitoring via Datadog; manual capacity reviews quarterly | G9: ◑ Partial | H9: No formal capacity management plan; thresholds not documented; no automated alerting for capacity breaches; DORA Art.9(3) requires monitoring and capacity planning | I9: Formalise capacity management plan; set and automate threshold alerts; integrate with incident management; annual forecast review | J9: Medium | K9: 2026-12-31 | L9: IT Infrastructure
A10: ICT Risk Management | B10: Data governance and data integrity | C10: Art. 9(3) | D10: A.8.9, A.8.10 | E10: MaRisk BTO 1.2 | F10: Data classification policy exists; some data quality controls in ABACUS | G10: ◑ Partial | H10: No enterprise data governance framework; data lineage not documented for regulatory reporting data; integrity checks inconsistent across systems | I10: Implement data governance framework; document data lineage for BaFin reporting data; enforce integrity controls across critical systems | J10: Medium | K10: 2027-01-31 | L10: CDO / CFO
A11: ICT Incident Management & Reporting | B11: Incident classification and detection | C11: Art. 17 | D11: A.5.25, A.5.26 | E11: BAIT §8; MaRisk AT 7.3 | F11: SIEM (Splunk) deployed; incident management via JIRA | G11: ◑ Partial | H11: No DORA-specific incident classification matrix; severity inconsistent across teams; Art.17 requires classification against DORA major incident criteria (clients affected, duration, data loss) | I11: Implement DORA classification matrix aligned to Art.17 criteria; train all first-line teams; embed in SIEM playbooks | J11: Critical | K11: 2026-07-31 | L11: CRO / CISO
A12: ICT Incident Management & Reporting | B12: Major incident initial notification (4h) | C12: Art. 19 | D12: A.5.26 | E12: BAIT §8 | F12: Manual BaFin reporting process; escalation procedure exists | G12: ✘ Missing | H12: No automated workflow for DORA 4h initial notification to BaFin; manual process consistently exceeds 4h; no integration with BaFin reporting portal | I12: Build automated DORA major incident reporting workflow; integrate with BaFin MIDAS portal; test notification workflow quarterly | J12: Critical | K12: 2026-08-31 | L12: CRO / Compliance
A13: ICT Incident Management & Reporting | B13: Intermediate report (72h) | C13: Art. 19 | D13: A.5.26 | E13: BAIT §8 | F13: Post-incident reviews documented; no structured intermediate reporting | G13: ◑ Partial | H13: No defined process for intermediate report at 72h; report templates not aligned to EBA/ESMA ITS format; intermediate trigger criteria undefined | I13: Adopt EBA ITS incident report templates; define 72h intermediate report trigger and mandatory content; test with tabletop exercise | J13: High | K13: 2026-09-30 | L13: CRO
... A35: Cross-cutting (DORA Art.30 / CIF) | B35: NIS2 alignment (where applicable) | C35: NIS2 / DORA Art.1(2) | D35: A.5.23 | E35: MaRisk AT 7.2 | F35: NIS2 applicability assessment not completed | G35: ◑ Partial | H35: Musterbank may be classified as 'essential' or 'important' entity under NIS2; NIS2 and DORA overlap in incident reporting, supply chain risk, and board accountability; alignment not assessed | I35: Complete NIS2 applicability assessment; map overlap with DORA controls; avoid duplication; notify BSI if NIS2 registration required | J35: Medium | K35: 2026-12-31 | L35: CRO / Legal
A38: KEY | ✔ Met = control fully satisfies DORA requirement | ◑ Partial = control exists but gaps remain | ✘ Missing = no current control — immediate remediation required | CIF = Critical or Important Function per DORA Art.28 / EBA ITS | BAIT = BaFin IT-Aufsichtsanforderungen | MaRisk = BaFin Mindestanforderungen an das Risikomanagement

Sheet Vendor Risk (Art.28)
A1: ICT Third-Party Risk Register — Musterbank GmbH | DORA Article 28 & Register of Information
A2: Vendor Name | B2: Service Provided | C2: Criticality | D2: DORA Art.28 Classification | E2: Contract Art.30 Clauses | F2: SLA (Availability) | G2: Risk Rating | H2: Concentration Risk | I2: Exit Plan Status | J2: Last Assessment | K2: Next Assessment | L2: Key Finding | M2: Action Required
A3: AWS (Amazon Web Services) | B3: Cloud infrastructure (IaaS/PaaS) – 70% of ICT services | C3: Critical | D3: ICT TPP – Critical | E3: ◑ Partial – re-papering in progress | F3: 99.99% | G3: Critical | H3: HIGH – single provider >60% | I3: ✘ Missing | J3: 2025-11-01 | K3: 2026-11-01 | L3: Concentration risk: 70% of critical ICT services on single provider. No multi-cloud failover; no tested exit plan. Consistent with R-003 (Gross 25 – Critical; CE 25%). Art.30 clauses 60% inserted. | M3: Complete Art.30 clauses by Dec 2026; draft and test full exit plan; implement multi-cloud Azure EU pilot; reduce concentration to ≤55%
A4: Temenos (T24 Core Banking) | B4: Core banking platform – account management, payments | C4: Critical | D4: ICT TPP – Critical | E4: ◑ Partial | F4: 99.9% | G4: Critical | H4: HIGH – no alternative | I4: ✘ Missing | J4: 2025-09-01 | K4: 2026-09-01 | L4: Forced exit timeline >24 months; data portability never tested; proprietary data formats; no exit plan; no transition budget. Consistent with R-010 (Gross 20 – Critical; CE 25%). | M4: Draft and board-approve full exit plan; test data portability; commission transition cost estimate; include in Register of Information
A5: Microsoft 365 | B5: Email, collaboration, Azure AD identity | C5: Critical | D5: ICT TPP – Critical | E5: ✔ Met | F5: 99.9% | G5: Medium | H5: MEDIUM – alternatives exist | I5: ◑ Partial – draft only | J5: 2026-01-01 | K5: 2027-01-01 | L5: Azure AD is central identity; outage impacts all staff; MFA enforced | M5: Finalise exit plan; ensure on-premise AD fallback is tested
A6: Finastra (Fusion Payments) | B6: Payment processing and SWIFT connectivity | C6: Critical | D6: ICT TPP – Critical | E6: ◑ Partial | F6: 99.95% | G6: High | H6: MEDIUM | I6: ◑ Partial – draft only | J6: 2026-02-01 | K6: 2027-02-01 | L6: SWIFT connectivity creates systemic risk; dual-authorisation controls in place | M6: Insert Art.30 clauses; document sub-outsourcing chain
A7: Salesforce | B7: CRM – customer data management | C7: Significant | D7: ICT TPP – Significant | E7: ✔ Met | F7: 99.9% | G7: Medium | H7: LOW | I7: ✔ Documented | J7: 2026-03-01 | K7: 2027-03-01 | L7: PII stored on US servers; DSGVO SCCs in place; data residency reviewed | M7: Annual review; confirm SCCs remain current post-Schrems III developments
A8: ABACUS (Wolters Kluwer) | B8: Regulatory reporting – BaFin COREP/FINREP | C8: Critical | D8: ICT TPP – Critical | E8: ◑ Partial | F8: 99.5% | G8: Critical | H8: MEDIUM – few alternatives | I8: ✘ Missing | J8: 2025-10-01 | K8: 2026-10-01 | L8: Single instance; DR drill April 2026 partial pass; manual fallback process not fully validated. Consistent with R-011 (Gross 12 – High; CE 50%). | M8: Provision DR instance; test manual fallback; insert Art.30 clauses
A9: Splunk | B9: SIEM – security monitoring and incident detection | C9: Significant | D9: ICT TPP – Significant | E9: ◑ Partial | F9: 99.5% | G9: Medium | H9: LOW | I9: ◑ Partial | J9: 2026-04-01 | K9: 2027-04-01 | L9: Logs held in US; data residency policy under review | M9: Confirm log residency; evaluate EU-hosted alternative
A10: OneTrust | B10: GRC platform – policy, vendor and privacy management | C10: Non-critical | D10: ICT TPP – Non-critical | E10: ✔ Met | F10: 99.9% | G10: Low | H10: LOW | I10: ✔ Documented | J10: 2026-05-01 | K10: 2027-05-01 | L10: Low risk; data limited to non-personal GRC metadata | M10: No immediate action; maintain annual review
